{
  "service": {
    "service": "alexa-chess",
    "serviceObject": {
      "name": "alexa-chess"
    },
    "provider": {
      "stage": "dev",
      "variableSyntax": "\\${([^{}]+?)}",
      "name": "aws",
      "runtime": "python3.7",
      "region": "us-east-1",
      "deploymentBucket": "456348640761-alexa-chess-dev",
      "profile": "alexa-chess-deploy",
      "versionFunctions": true,
      "remoteFunctionData": null,
      "compiledCloudFormationTemplate": {
        "AWSTemplateFormatVersion": "2010-09-09",
        "Description": "CloudFormation template generated by serverless framework",
        "Resources": {
          "AlexaUnderscorechessUnderscorehandlerLogGroup": {
            "Type": "AWS::Logs::LogGroup",
            "Properties": {
              "LogGroupName": "/aws/lambda/alexa-chess-dev-alexa_chess_handler"
            }
          },
          "IamRoleLambdaExecution": {
            "Type": "AWS::IAM::Role",
            "Properties": {
              "AssumeRolePolicyDocument": {
                "Version": "2012-10-17",
                "Statement": [
                  {
                    "Effect": "Allow",
                    "Principal": {
                      "Service": [
                        "lambda.amazonaws.com"
                      ]
                    },
                    "Action": [
                      "sts:AssumeRole"
                    ]
                  }
                ]
              },
              "Policies": [
                {
                  "PolicyName": {
                    "Fn::Join": [
                      "-",
                      [
                        "alexa-chess-dev",
                        "lambda"
                      ]
                    ]
                  },
                  "PolicyDocument": {
                    "Version": "2012-10-17",
                    "Statement": [
                      {
                        "Effect": "Allow",
                        "Action": [
                          "logs:CreateLogStream",
                          "logs:CreateLogGroup"
                        ],
                        "Resource": [
                          {
                            "Fn::Sub": "arn:${AWS::Partition}:logs:${AWS::Region}:${AWS::AccountId}:log-group:/aws/lambda/alexa-chess-dev*:*"
                          }
                        ]
                      },
                      {
                        "Effect": "Allow",
                        "Action": [
                          "logs:PutLogEvents"
                        ],
                        "Resource": [
                          {
                            "Fn::Sub": "arn:${AWS::Partition}:logs:${AWS::Region}:${AWS::AccountId}:log-group:/aws/lambda/alexa-chess-dev*:*:*"
                          }
                        ]
                      }
                    ]
                  }
                }
              ],
              "Path": "/",
              "RoleName": {
                "Fn::Join": [
                  "-",
                  [
                    "alexa-chess-dev",
                    {
                      "Ref": "AWS::Region"
                    },
                    "lambdaRole"
                  ]
                ]
              }
            }
          },
          "AlexaUnderscorechessUnderscorehandlerLambdaFunction": {
            "Type": "AWS::Lambda::Function",
            "Properties": {
              "Code": {
                "S3Bucket": "456348640761-alexa-chess-dev",
                "S3Key": "serverless/alexa-chess/dev/1588128661838-2020-04-29T02:51:01.838Z/alexa-chess.zip"
              },
              "FunctionName": "alexa-chess-dev-alexa_chess_handler",
              "Handler": "src/alexa_chess_handler.lambda_handler",
              "MemorySize": 128,
              "Role": {
                "Fn::GetAtt": [
                  "AlexaUnderscorechessUnderscorehandlerIamRoleLambdaExecution",
                  "Arn"
                ]
              },
              "Runtime": "python3.7",
              "Timeout": 15,
              "Description": "Controls Alexa responses for Alexa Chess",
              "Environment": {
                "Variables": {
                  "ENV": "environment",
                  "BOARD_IMAGES_BUCKET": "456348640761-alexa-chess-dev-board-images"
                }
              }
            },
            "DependsOn": [
              "AlexaUnderscorechessUnderscorehandlerIamRoleLambdaExecution",
              "AlexaUnderscorechessUnderscorehandlerLogGroup"
            ]
          },
          "AlexaUnderscorechessUnderscorehandlerLambdaVersion3UlDr8hS7HRmzyI9dMZGdCxKft5lLv23x3E9WT4": {
            "Type": "AWS::Lambda::Version",
            "DeletionPolicy": "Retain",
            "Properties": {
              "FunctionName": {
                "Ref": "AlexaUnderscorechessUnderscorehandlerLambdaFunction"
              },
              "CodeSha256": "ctJDekVRDerHZS+lLmSJTk4bmOSWEMQtVGiWC5+RQh0=",
              "Description": "Controls Alexa responses for Alexa Chess"
            }
          },
          "AlexaUnderscorechessUnderscorehandlerLambdaPermissionAlexaSkill1": {
            "Type": "AWS::Lambda::Permission",
            "Properties": {
              "FunctionName": {
                "Fn::GetAtt": [
                  "AlexaUnderscorechessUnderscorehandlerLambdaFunction",
                  "Arn"
                ]
              },
              "Action": "lambda:InvokeFunction",
              "Principal": "alexa-appkit.amazon.com",
              "EventSourceToken": "amzn1.ask.skill.d79d3e65-2090-45c3-938a-0c6c7e26071f"
            }
          },
          "AlexaUnderscorechessUnderscorehandlerIamRoleLambdaExecution": {
            "Type": "AWS::IAM::Role",
            "Properties": {
              "AssumeRolePolicyDocument": {
                "Version": "2012-10-17",
                "Statement": [
                  {
                    "Effect": "Allow",
                    "Principal": {
                      "Service": [
                        "lambda.amazonaws.com"
                      ]
                    },
                    "Action": [
                      "sts:AssumeRole"
                    ]
                  }
                ]
              },
              "Policies": [
                {
                  "PolicyName": {
                    "Fn::Join": [
                      "-",
                      [
                        "alexa-chess-dev",
                        "lambda"
                      ]
                    ]
                  },
                  "PolicyDocument": {
                    "Version": "2012-10-17",
                    "Statement": [
                      {
                        "Effect": "Allow",
                        "Action": [
                          "logs:CreateLogStream",
                          "logs:PutLogEvents"
                        ],
                        "Resource": [
                          {
                            "Fn::Sub": "arn:${AWS::Partition}:logs:${AWS::Region}:${AWS::AccountId}:log-group:/aws/lambda/alexa-chess-dev-alexa_chess_handler:*:*"
                          }
                        ]
                      },
                      {
                        "Effect": "Allow",
                        "Action": [
                          "lambda:GetLayerVersion",
                          "lambda:PublishLayerVersion"
                        ],
                        "Resource": "*"
                      },
                      {
                        "Effect": "Allow",
                        "Action": [
                          "logs:CreateLogGroup",
                          "logs:CreateLogStream",
                          "logs:PutLogEvents"
                        ],
                        "Resource": "arn:aws:logs:*:*:*"
                      },
                      {
                        "Effect": "Allow",
                        "Action": [
                          "s3:PutObject",
                          "s3:GetObject",
                          "s3:GetObjectVersion",
                          "s3:ListBucket"
                        ],
                        "Resource": {
                          "Fn::Join": [
                            "",
                            [
                              "arn:aws:s3:::",
                              "456348640761-alexa-chess-dev-board-images",
                              "/*"
                            ]
                          ]
                        }
                      }
                    ]
                  }
                }
              ],
              "Path": "/",
              "RoleName": "alexa-chess-handler-role-dev",
              "ManagedPolicyArns": []
            }
          },
          "BoardImagesBucket": {
            "Type": "AWS::S3::Bucket",
            "Properties": {
              "BucketName": "456348640761-alexa-chess-dev-board-images",
              "LifecycleConfiguration": {
                "Rules": [
                  {
                    "Id": "DeleteContentAfter1Day",
                    "Prefix": "",
                    "Status": "Enabled",
                    "ExpirationInDays": "1"
                  }
                ]
              }
            }
          }
        },
        "Outputs": {
          "ServerlessDeploymentBucketName": {
            "Value": "456348640761-alexa-chess-dev"
          },
          "AlexaUnderscorechessUnderscorehandlerLambdaFunctionQualifiedArn": {
            "Description": "Current Lambda function version",
            "Value": {
              "Ref": "AlexaUnderscorechessUnderscorehandlerLambdaVersion3UlDr8hS7HRmzyI9dMZGdCxKft5lLv23x3E9WT4"
            }
          }
        }
      },
      "vpc": {}
    },
    "custom": {
      "pythonRequirements": {
        "dockerizePip": "non-linux"
      },
      "account_id": "456348640761",
      "stage": "dev",
      "region": "us-east-1",
      "deployment_bucket": "456348640761-alexa-chess-dev",
      "session_table": "456348640761-alexa-chess-dev-session",
      "board_images_bucket": "456348640761-alexa-chess-dev-board-images"
    },
    "plugins": [
      "serverless-python-requirements",
      "serverless-iam-roles-per-function",
      "serverless-pseudo-parameters",
      "serverless-plugin-create-deployment-bucket"
    ],
    "pluginsData": {},
    "functions": {
      "alexa_chess_handler": {
        "handler": "src/alexa_chess_handler.lambda_handler",
        "description": "Controls Alexa responses for Alexa Chess",
        "memorySize": 128,
        "timeout": 15,
        "environment": {
          "ENV": "environment",
          "BOARD_IMAGES_BUCKET": "456348640761-alexa-chess-dev-board-images"
        },
        "iamRoleStatementsName": "alexa-chess-handler-role-dev",
        "iamRoleStatements": [
          {
            "$ref": "$[\"service\"][\"provider\"][\"compiledCloudFormationTemplate\"][\"Resources\"][\"AlexaUnderscorechessUnderscorehandlerIamRoleLambdaExecution\"][\"Properties\"][\"Policies\"][0][\"PolicyDocument\"][\"Statement\"][1]"
          },
          {
            "$ref": "$[\"service\"][\"provider\"][\"compiledCloudFormationTemplate\"][\"Resources\"][\"AlexaUnderscorechessUnderscorehandlerIamRoleLambdaExecution\"][\"Properties\"][\"Policies\"][0][\"PolicyDocument\"][\"Statement\"][2]"
          },
          {
            "$ref": "$[\"service\"][\"provider\"][\"compiledCloudFormationTemplate\"][\"Resources\"][\"AlexaUnderscorechessUnderscorehandlerIamRoleLambdaExecution\"][\"Properties\"][\"Policies\"][0][\"PolicyDocument\"][\"Statement\"][3]"
          }
        ],
        "events": [
          {
            "alexaSkill": "amzn1.ask.skill.d79d3e65-2090-45c3-938a-0c6c7e26071f"
          }
        ],
        "name": "alexa-chess-dev-alexa_chess_handler",
        "package": {},
        "memory": 128,
        "runtime": "python3.7",
        "vpc": {},
        "versionLogicalId": "AlexaUnderscorechessUnderscorehandlerLambdaVersion3UlDr8hS7HRmzyI9dMZGdCxKft5lLv23x3E9WT4"
      }
    },
    "resources": {
      "Description": "CloudFormation template generated by serverless framework",
      "Resources": {
        "BoardImagesBucket": {
          "Type": "AWS::S3::Bucket",
          "Properties": {
            "BucketName": "456348640761-alexa-chess-dev-board-images",
            "LifecycleConfiguration": {
              "Rules": [
                {
                  "Id": "DeleteContentAfter1Day",
                  "Prefix": "",
                  "Status": "Enabled",
                  "ExpirationInDays": "1"
                }
              ]
            }
          }
        }
      },
      "Outputs": {}
    },
    "serviceFilename": "serverless.yml",
    "layers": {},
    "isDashboardMonitoringPreconfigured": false,
    "artifact": "/Users/filipebarretto/Documents/git/alexa-chess/alexa_controller/.serverless/alexa-chess.zip"
  },
  "package": {
    "artifactDirectoryName": "serverless/alexa-chess/dev/1588128661838-2020-04-29T02:51:01.838Z",
    "artifact": "alexa-chess.zip"
  }
}